Metadata-Version: 2.1
Name: Gaussian-Theorem
Version: 1.0
Summary: Gaussian and Binomial distributions
Author: Makoha Dharren Pius
Author-email: dharrenpius@outlook.com
